{
    "id":  "enemy_saurian_t2_03",
    "name":  "Pachycephalosaurus Charger",
    "category":  "enemies",
    "sourceFile":  "saurian",
    "status":  "pending",
    "sourceDescription":  "anthropomorphic Pachycephalosaurus, reinforced skull plate with a war hammer, brigandine vest over tunic, wielding a war hammer-handed war hammer, no helmet (thick skull)",
    "files":  {
                  "original":  "assets/images/enemies/saurian_t2_03_original.png"
              },
    "lastUpdated":  "2026-01-15T01:02:30.376456"
}
