[
    {
        "id": "salvage_t1_01",
        "name": "Scrap Iron",
        "tier": 1,
        "source": "Enemy Soldiers, Debris",
        "location": "biome",
        "biome": "all",
        "rarity": "common",
        "status": "pending"
    },
    {
        "id": "salvage_t2_02",
        "name": "Black Powder",
        "tier": 2,
        "source": "Enemy Soldiers",
        "location": "biome",
        "biome": "all",
        "rarity": "uncommon",
        "status": "pending"
    },
    {
        "id": "salvage_t1_03",
        "name": "Ration Tin",
        "tier": 1,
        "source": "Enemy Soldiers",
        "location": "biome",
        "biome": "all",
        "rarity": "common",
        "status": "pending"
    },
    {
        "id": "salvage_t2_04",
        "name": "Brass Casing",
        "tier": 2,
        "source": "Enemy Soldiers",
        "location": "biome",
        "biome": "all",
        "rarity": "common",
        "status": "pending"
    },
    {
        "id": "salvage_t2_05",
        "name": "Mechanical Parts",
        "tier": 2,
        "source": "Enemy Sergeants, Machinery",
        "location": "biome",
        "biome": "all",
        "rarity": "uncommon",
        "status": "pending"
    },
    {
        "id": "salvage_t3_06",
        "name": "Munitions",
        "tier": 3,
        "source": "Ammo Crate, Officers",
        "location": "biome",
        "biome": "all",
        "rarity": "uncommon",
        "status": "pending"
    }
]